sherpa_onnx/__init__.py
sherpa_onnx/cli.py
sherpa_onnx/display.py
sherpa_onnx/keyword_spotter.py
sherpa_onnx/offline_recognizer.py
sherpa_onnx/online_recognizer.py
sherpa_onnx/utils.py
sherpa_onnx/lib/_sherpa_onnx.cp39-win32.pyd
sherpa_onnx-1.12.23.dist-info/licenses/LICENSE
sherpa_onnx-1.12.23.dist-info/METADATA
sherpa_onnx-1.12.23.dist-info/WHEEL
sherpa_onnx-1.12.23.dist-info/entry_points.txt
sherpa_onnx-1.12.23.dist-info/top_level.txt
sherpa_onnx-1.12.23.dist-info/RECORD
