Metadata-Version: 2.4
Name: sherpa_onnx
Version: 1.12.23
Home-page: https://github.com/k2-fsa/sherpa-onnx
Author: The sherpa-onnx development team
Author-email: dpovey@gmail.com
License: Apache licensed, as found in the LICENSE file
Classifier: Programming Language :: C++
Classifier: Programming Language :: Python
Classifier: Topic :: Scientific/Engineering :: Artificial Intelligence
Requires-Python: >=3.7
License-File: LICENSE
Requires-Dist: sherpa-onnx-core==1.12.23
Dynamic: author
Dynamic: author-email
Dynamic: classifier
Dynamic: description
Dynamic: description-content-type
Dynamic: home-page
Dynamic: license
Dynamic: license-file
Dynamic: requires-dist
Dynamic: requires-python
